dbk11/__init__.py
dbk11/aa.py
dbk11-0.1.0.dist-info/METADATA
dbk11-0.1.0.dist-info/WHEEL
dbk11-0.1.0.dist-info/top_level.txt
dbk11-0.1.0.dist-info/RECORD
